quarchCalibration/BK9832B.py
quarchCalibration/ET2260.py
quarchCalibration/Keithley_DMM6500_control.py
quarchCalibration/Keysight_AC6804B_control.py
quarchCalibration/PowerModuleCalibration.py
quarchCalibration/QTL1944_06_hd_plus_ppm.py
quarchCalibration/QTL1944_hd_ppm.py
quarchCalibration/QTL2347_pcie.py
quarchCalibration/QTL2525_sff.py
quarchCalibration/QTL2536_6_way_switchbox.py
quarchCalibration/QTL2582_3ph_ac.py
quarchCalibration/QTL2621_2ch_mezz.py
quarchCalibration/QTL2626_4ch_mezz.py
quarchCalibration/QTL2628_ext_mezz_dimm.py
quarchCalibration/QTL2631_ext_mezz.py
quarchCalibration/QTL2631_pcie.py
quarchCalibration/QTL2673_edsff.py
quarchCalibration/QTL2843_iec_ac.py
quarchCalibration/__init__.py
quarchCalibration/__main__.py
quarchCalibration/_version.py
quarchCalibration/acHelpers.py
quarchCalibration/calibrationConfig.py
quarchCalibration/calibrationUtil.py
quarchCalibration/deviceHelpers.py
quarchCalibration/elpaSine.py
quarchCalibration/keithley_2460_control.py
quarchCalibration/pamCommon.py
quarchCalibration/pamHelpers.py
quarchCalibration/threePhaseSwitchBox.py
quarchCalibration/docs/__init__.py
quarchCalibration/docs/conf.py
quarchCalibration-1.1.20.dist-info/METADATA
quarchCalibration-1.1.20.dist-info/WHEEL
quarchCalibration-1.1.20.dist-info/top_level.txt
quarchCalibration-1.1.20.dist-info/RECORD
