Metadata-Version: 2.1
Name: quarchCalibration
Version: 1.1.20
Summary: This packpage offers calibration for Quarch Technology modules.
Author: Quarch Technology ltd
Author-email: support@quarch.com
License: Quarch Technology ltd
Keywords: quarch quarchpy calibration torridon
Classifier: Intended Audience :: Information Technology
Classifier: Intended Audience :: Developers
Classifier: Natural Language :: English
Classifier: Operating System :: MacOS
Classifier: Operating System :: Microsoft :: Windows
Classifier: Operating System :: POSIX
Classifier: Programming Language :: Python
Classifier: Topic :: Scientific/Engineering :: Information Analysis
Classifier: Topic :: System
Classifier: Topic :: System :: Power (UPS)
